jupyterlab_rise_metadata_form/__init__.py
jupyterlab_rise_metadata_form/_version.py
jupyterlab_rise_metadata_form-1.0.1.data/data/share/jupyter/labextensions/@jans-code/jupyterlab_rise_metadata_form/package.json
jupyterlab_rise_metadata_form-1.0.1.data/data/share/jupyter/labextensions/@jans-code/jupyterlab_rise_metadata_form/schemas/@jans-code/jupyterlab_rise_metadata_form/package.json.orig
jupyterlab_rise_metadata_form-1.0.1.data/data/share/jupyter/labextensions/@jans-code/jupyterlab_rise_metadata_form/schemas/@jans-code/jupyterlab_rise_metadata_form/risemdf.json
jupyterlab_rise_metadata_form-1.0.1.data/data/share/jupyter/labextensions/@jans-code/jupyterlab_rise_metadata_form/static/509.82c83d88a314838bd37c.js
jupyterlab_rise_metadata_form-1.0.1.data/data/share/jupyter/labextensions/@jans-code/jupyterlab_rise_metadata_form/static/728.8dcd6beb31a2181fb758.js
jupyterlab_rise_metadata_form-1.0.1.data/data/share/jupyter/labextensions/@jans-code/jupyterlab_rise_metadata_form/static/remoteEntry.952aa98dd7822da17116.js
jupyterlab_rise_metadata_form-1.0.1.data/data/share/jupyter/labextensions/@jans-code/jupyterlab_rise_metadata_form/static/style.js
jupyterlab_rise_metadata_form-1.0.1.data/data/share/jupyter/labextensions/@jans-code/jupyterlab_rise_metadata_form/static/third-party-licenses.json
jupyterlab_rise_metadata_form-1.0.1.data/data/share/jupyter/labextensions/@jans-code/jupyterlab_rise_metadata_form/install.json
jupyterlab_rise_metadata_form-1.0.1.dist-info/METADATA
jupyterlab_rise_metadata_form-1.0.1.dist-info/WHEEL
jupyterlab_rise_metadata_form-1.0.1.dist-info/licenses/LICENSE
jupyterlab_rise_metadata_form-1.0.1.dist-info/RECORD
