Metadata-Version: 2.3
Name: jupyterlab_rise_metadata_form
Version: 1.0.1
Dynamic: Keywords
Summary: Jupyterlab rise metadata form extension.
Project-URL: Homepage, https://github.com/jans-code/jupyterlab_rise_metadata_form
Project-URL: Bug Tracker, https://github.com/jans-code/jupyterlab_rise_metadata_form/issues
Project-URL: Repository, https://github.com/jans-code/jupyterlab_rise_metadata_form.git
Author: Project Jupyter Contributors
License: BSD-3-Clause License
License-File: LICENSE
Classifier: Framework :: Jupyter
Classifier: Framework :: Jupyter :: JupyterLab
Classifier: Framework :: Jupyter :: JupyterLab :: 4
Classifier: Framework :: Jupyter :: JupyterLab :: Extensions
Classifier: Framework :: Jupyter :: JupyterLab :: Extensions :: Prebuilt
Classifier: License :: OSI Approved :: BSD License
Classifier: Programming Language :: Python
Classifier: Programming Language :: Python :: 3
Classifier: Programming Language :: Python :: 3.8
Classifier: Programming Language :: Python :: 3.9
Classifier: Programming Language :: Python :: 3.10
Classifier: Programming Language :: Python :: 3.11
Classifier: Programming Language :: Python :: 3.12
Requires-Python: >=3.8
